YorkUphysLab/__init__.py
YorkUphysLab/__version__.py
YorkUphysLab/Actuator/Actuator.py
YorkUphysLab/Actuator/__init__.py
YorkUphysLab/GwINSTEK/AFG2000.py
YorkUphysLab/GwINSTEK/GPD3303D.py
YorkUphysLab/GwINSTEK/__init__.py
YorkUphysLab/HVcontrol/HV_control.py
YorkUphysLab/HVcontrol/__init__.py
YorkUphysLab/ScoutScale/ScoutSTX.py
YorkUphysLab/ScoutScale/__init__.py
YorkUphysLab/Tektronix/TBS1000.py
YorkUphysLab/Tektronix/__init__.py
YorkUphysLab/Utility/Utility.py
YorkUphysLab/Utility/__init__.py
YorkUphysLab-1.0.27.dist-info/LICENSE
YorkUphysLab-1.0.27.dist-info/METADATA
YorkUphysLab-1.0.27.dist-info/WHEEL
YorkUphysLab-1.0.27.dist-info/top_level.txt
YorkUphysLab-1.0.27.dist-info/RECORD
