Metadata-Version: 2.1
Name: YorkUphysLab
Version: 1.0.27
Summary: A Python package to control YU physics labs equipment
Home-page: https://github.com/m-kareem/YorkUphysLab
Author: Mohammad Kareem
Author-email: mkareem@yorku.ca
Project-URL: Bug Tracker, https://github.com/m-kareem/YorkUphysLab/issues
Project-URL: repository, https://github.com/m-kareem/YorkUphysLab
Classifier: Programming Language :: Python :: 3
Classifier: License :: OSI Approved :: MIT License
Classifier: Operating System :: OS Independent
Requires-Python: >=3.7
License-File: LICENSE
Requires-Dist: nidaqmx ==0.7.0
Requires-Dist: pyserial ==3.5
Requires-Dist: pyvisa-py ==0.7.1
Requires-Dist: numpy ==1.23.5
